pyqt_popup_graphics_view/__init__.py
pyqt_popup_graphics_view/imagePopupGraphicsView.py
pyqt_popup_graphics_view/popupGraphicsView.py
pyqt_popup_graphics_view-0.0.1.dist-info/LICENSE
pyqt_popup_graphics_view-0.0.1.dist-info/METADATA
pyqt_popup_graphics_view-0.0.1.dist-info/WHEEL
pyqt_popup_graphics_view-0.0.1.dist-info/top_level.txt
pyqt_popup_graphics_view-0.0.1.dist-info/RECORD
