Metadata-Version: 2.1
Name: pyqt-popup-graphics-view
Version: 0.0.1
Summary: PyQt popup QGraphicsView (image will pop up when move the mouse cursor inside the QGraphicsView)
Home-page: https://github.com/yjg30737/pyqt-popup-graphics-view.git
Author: Jung Gyu Yoon
Author-email: yjg30737@gmail.com
License: GPL 3.0
Platform: UNKNOWN
License-File: LICENSE
Requires-Dist: PyQt5 (>=5.8)
